[
  {
    "TYPE": "NORMAL",
    "NORMAL": 1,
    "FIGHTING": 1,
    "FLYING": 1,
    "POISON": 1,
    "GROUND": 1,
    "ROCK": 0.8,
    "BUG": 1,
    "GHOST": 0.8,
    "STEEL": 0.8,
    "FIRE": 1,
    "WATER": 1,
    "GRASS": 1,
    "ELECTRIC": 1,
    "PSYCHIC": 1,
    "ICE": 1,
    "DRAGON": 1,
    "DARK": 1,
    "FAIRY": 1
  },
  {
    "TYPE": "FIGHTING",
    "NORMAL": 1.25,
    "FIGHTING": 1,
    "FLYING": 0.8,
    "POISON": 0.8,
    "GROUND": 1,
    "ROCK": 1.25,
    "BUG": 0.8,
    "GHOST": 0.8,
    "STEEL": 1.25,
    "FIRE": 1,
    "WATER": 1,
    "GRASS": 1,
    "ELECTRIC": 1,
    "PSYCHIC": 0.8,
    "ICE": 1.25,
    "DRAGON": 1,
    "DARK": 1.25,
    "FAIRY": 0.8
  },
  {
    "TYPE": "FLYING",
    "NORMAL": 1,
    "FIGHTING": 1.25,
    "FLYING": 1,
    "POISON": 1,
    "GROUND": 1,
    "ROCK": 0.8,
    "BUG": 1.25,
    "GHOST": 1,
    "STEEL": 0.8,
    "FIRE": 1,
    "WATER": 1,
    "GRASS": 1.25,
    "ELECTRIC": 0.8,
    "PSYCHIC": 1,
    "ICE": 1,
    "DRAGON": 1,
    "DARK": 1,
    "FAIRY": 1
  },
  {
    "TYPE": "POISON",
    "NORMAL": 1,
    "FIGHTING": 1,
    "FLYING": 1,
    "POISON": 0.8,
    "GROUND": 0.8,
    "ROCK": 0.8,
    "BUG": 1,
    "GHOST": 0.8,
    "STEEL": 0.8,
    "FIRE": 1,
    "WATER": 1,
    "GRASS": 1.25,
    "ELECTRIC": 1,
    "PSYCHIC": 1,
    "ICE": 1,
    "DRAGON": 1,
    "DARK": 1,
    "FAIRY": 1.25
  },
  {
    "TYPE": "GROUND",
    "NORMAL": 1,
    "FIGHTING": 1,
    "FLYING": 0.8,
    "POISON": 1.25,
    "GROUND": 1,
    "ROCK": 1.25,
    "BUG": 0.8,
    "GHOST": 1,
    "STEEL": 1.25,
    "FIRE": 1.25,
    "WATER": 1,
    "GRASS": 0.8,
    "ELECTRIC": 1.25,
    "PSYCHIC": 1,
    "ICE": 1,
    "DRAGON": 1,
    "DARK": 1,
    "FAIRY": 1
  },
  {
    "TYPE": "ROCK",
    "NORMAL": 1,
    "FIGHTING": 0.8,
    "FLYING": 1.25,
    "POISON": 1,
    "GROUND": 0.8,
    "ROCK": 1,
    "BUG": 1.25,
    "GHOST": 1,
    "STEEL": 0.8,
    "FIRE": 1.25,
    "WATER": 1,
    "GRASS": 1,
    "ELECTRIC": 1,
    "PSYCHIC": 1,
    "ICE": 1.25,
    "DRAGON": 1,
    "DARK": 1,
    "FAIRY": 1
  },
  {
    "TYPE": "BUG",
    "NORMAL": 1,
    "FIGHTING": 0.8,
    "FLYING": 0.8,
    "POISON": 0.8,
    "GROUND": 1,
    "ROCK": 1,
    "BUG": 1,
    "GHOST": 0.8,
    "STEEL": 0.8,
    "FIRE": 0.8,
    "WATER": 1,
    "GRASS": 1.25,
    "ELECTRIC": 1,
    "PSYCHIC": 1.25,
    "ICE": 1,
    "DRAGON": 1,
    "DARK": 1.25,
    "FAIRY": 0.8
  },
  {
    "TYPE": "GHOST",
    "NORMAL": 0.8,
    "FIGHTING": 1,
    "FLYING": 1,
    "POISON": 1,
    "GROUND": 1,
    "ROCK": 1,
    "BUG": 1,
    "GHOST": 1.25,
    "STEEL": 1,
    "FIRE": 1,
    "WATER": 1,
    "GRASS": 1,
    "ELECTRIC": 1,
    "PSYCHIC": 1.25,
    "ICE": 1,
    "DRAGON": 1,
    "DARK": 0.8,
    "FAIRY": 1
  },
  {
    "TYPE": "STEEL",
    "NORMAL": 1,
    "FIGHTING": 1,
    "FLYING": 1,
    "POISON": 1,
    "GROUND": 1,
    "ROCK": 1.25,
    "BUG": 1,
    "GHOST": 1,
    "STEEL": 0.8,
    "FIRE": 0.8,
    "WATER": 0.8,
    "GRASS": 1,
    "ELECTRIC": 0.8,
    "PSYCHIC": 1,
    "ICE": 1.25,
    "DRAGON": 1,
    "DARK": 1,
    "FAIRY": 1.25
  },
  {
    "TYPE": "FIRE",
    "NORMAL": 1,
    "FIGHTING": 1,
    "FLYING": 1,
    "POISON": 1,
    "GROUND": 1,
    "ROCK": 0.8,
    "BUG": 1.25,
    "GHOST": 1,
    "STEEL": 1.25,
    "FIRE": 0.8,
    "WATER": 0.8,
    "GRASS": 1.25,
    "ELECTRIC": 1,
    "PSYCHIC": 1,
    "ICE": 1.25,
    "DRAGON": 0.8,
    "DARK": 1,
    "FAIRY": 1
  },
  {
    "TYPE": "WATER",
    "NORMAL": 1,
    "FIGHTING": 1,
    "FLYING": 1,
    "POISON": 1,
    "GROUND": 1.25,
    "ROCK": 1.25,
    "BUG": 1,
    "GHOST": 1,
    "STEEL": 1,
    "FIRE": 1.25,
    "WATER": 0.8,
    "GRASS": 0.8,
    "ELECTRIC": 1,
    "PSYCHIC": 1,
    "ICE": 1,
    "DRAGON": 0.8,
    "DARK": 1,
    "FAIRY": 1
  },
  {
    "TYPE": "GRASS",
    "NORMAL": 1,
    "FIGHTING": 1,
    "FLYING": 0.8,
    "POISON": 0.8,
    "GROUND": 1.25,
    "ROCK": 1.25,
    "BUG": 0.8,
    "GHOST": 1,
    "STEEL": 0.8,
    "FIRE": 0.8,
    "WATER": 1.25,
    "GRASS": 0.8,
    "ELECTRIC": 1,
    "PSYCHIC": 1,
    "ICE": 1,
    "DRAGON": 0.8,
    "DARK": 1,
    "FAIRY": 1
  },
  {
    "TYPE": "ELECTRIC",
    "NORMAL": 1,
    "FIGHTING": 1,
    "FLYING": 1.25,
    "POISON": 1,
    "GROUND": 0.8,
    "ROCK": 1,
    "BUG": 1,
    "GHOST": 1,
    "STEEL": 1,
    "FIRE": 1,
    "WATER": 1.25,
    "GRASS": 0.8,
    "ELECTRIC": 0.8,
    "PSYCHIC": 1,
    "ICE": 1,
    "DRAGON": 0.8,
    "DARK": 1,
    "FAIRY": 1
  },
  {
    "TYPE": "PSYCHIC",
    "NORMAL": 1,
    "FIGHTING": 1.25,
    "FLYING": 1,
    "POISON": 1.25,
    "GROUND": 1,
    "ROCK": 1,
    "BUG": 1,
    "GHOST": 1,
    "STEEL": 0.8,
    "FIRE": 1,
    "WATER": 1,
    "GRASS": 1,
    "ELECTRIC": 1,
    "PSYCHIC": 0.8,
    "ICE": 1,
    "DRAGON": 1,
    "DARK": 0.8,
    "FAIRY": 1
  },
  {
    "TYPE": "ICE",
    "NORMAL": 1,
    "FIGHTING": 1,
    "FLYING": 1.25,
    "POISON": 1,
    "GROUND": 1.25,
    "ROCK": 1,
    "BUG": 1,
    "GHOST": 1,
    "STEEL": 0.8,
    "FIRE": 0.8,
    "WATER": 0.8,
    "GRASS": 1.25,
    "ELECTRIC": 1,
    "PSYCHIC": 1,
    "ICE": 0.8,
    "DRAGON": 1.25,
    "DARK": 1,
    "FAIRY": 1
  },
  {
    "TYPE": "DRAGON",
    "NORMAL": 1,
    "FIGHTING": 1,
    "FLYING": 1,
    "POISON": 1,
    "GROUND": 1,
    "ROCK": 1,
    "BUG": 1,
    "GHOST": 1,
    "STEEL": 0.8,
    "FIRE": 1,
    "WATER": 1,
    "GRASS": 1,
    "ELECTRIC": 1,
    "PSYCHIC": 1,
    "ICE": 1,
    "DRAGON": 1.25,
    "DARK": 1,
    "FAIRY": 0.8
  },
  {
    "TYPE": "DARK",
    "NORMAL": 1,
    "FIGHTING": 0.8,
    "FLYING": 1,
    "POISON": 1,
    "GROUND": 1,
    "ROCK": 1,
    "BUG": 1,
    "GHOST": 1.25,
    "STEEL": 1,
    "FIRE": 1,
    "WATER": 1,
    "GRASS": 1,
    "ELECTRIC": 1,
    "PSYCHIC": 1.25,
    "ICE": 1,
    "DRAGON": 1,
    "DARK": 0.8,
    "FAIRY": 0.8
  },
  {
    "TYPE": "FAIRY",
    "NORMAL": 1,
    "FIGHTING": 1.25,
    "FLYING": 1,
    "POISON": 0.8,
    "GROUND": 1,
    "ROCK": 1,
    "BUG": 1,
    "GHOST": 1,
    "STEEL": 0.8,
    "FIRE": 0.8,
    "WATER": 1,
    "GRASS": 1,
    "ELECTRIC": 1,
    "PSYCHIC": 1,
    "ICE": 1,
    "DRAGON": 1.25,
    "DARK": 1.25,
    "FAIRY": 1
  }
]